gsloc/__init__.py
gsloc/cli.py
gsloc/core.py
gsloc/protobuf/__init__.py
gsloc/protobuf/location_pb2.py
gsloc/protobuf/location_pb2.pyi
gsloc-0.1.2.dist-info/METADATA
gsloc-0.1.2.dist-info/WHEEL
gsloc-0.1.2.dist-info/entry_points.txt
gsloc-0.1.2.dist-info/RECORD
