Metadata-Version: 2.1
Name: gsloc
Version: 0.1.2
Summary: A simple API for Apple's gs-loc service
Home-page: https://github.com/Microwave-WYB/gsloc
License: MIT
Author: Yibo Wei
Author-email: david_wyb2001@outlook.com
Requires-Python: >=3.7,<4.0
Classifier: License :: OSI Approved :: MIT License
Classifier: Programming Language :: Python :: 3
Classifier: Programming Language :: Python :: 3.7
Classifier: Programming Language :: Python :: 3.8
Classifier: Programming Language :: Python :: 3.9
Classifier: Programming Language :: Python :: 3.10
Classifier: Programming Language :: Python :: 3.11
Classifier: Programming Language :: Python :: 3.12
Requires-Dist: protobuf (>=5.26.1,<6.0.0)
Requires-Dist: requests (>=2.31.0,<3.0.0)
Requires-Dist: rich (>=13.7.1,<14.0.0)
Project-URL: Repository, https://github.com/Microwave-WYB/gsloc
